LICENSE
MANIFEST.in
README.md
setup.py
zhiming/__init__.py
zhiming/zhiming_settings.py
zhiming/zhiming_system.py
zhiming.egg-info/PKG-INFO
zhiming.egg-info/SOURCES.txt
zhiming.egg-info/dependency_links.txt
zhiming.egg-info/top_level.txt
zhiming/data_source/__init__.py
zhiming/data_source/data_source.py
zhiming/gui/__init__.py
zhiming/kernel/__init__.py
zhiming/kernel/performance.py