Metadata-Version: 2.1
Name: zhiming
Version: 0.0.1
Summary: A package for information and data analysis.
Home-page: https://github.com/Li-Ming-Fan/zhiming
Author: Ming-Fan Li
Author-email: li_m_f@163.com
Maintainer: Ming-Fan Li
Maintainer-email: li_m_f@163.com
License: UNKNOWN
Platform: any
